CHANGELOG.md
COPYING.txt
MANIFEST.in
README.rst
setup.cfg
setup.py
rattail_corepos/__init__.py
rattail_corepos/_version.py
rattail_corepos/app.py
rattail_corepos/auth.py
rattail_corepos/commands.py
rattail_corepos/config.py
rattail_corepos/emails.py
rattail_corepos/products.py
rattail_corepos.egg-info/PKG-INFO
rattail_corepos.egg-info/SOURCES.txt
rattail_corepos.egg-info/dependency_links.txt
rattail_corepos.egg-info/entry_points.txt
rattail_corepos.egg-info/not-zip-safe
rattail_corepos.egg-info/requires.txt
rattail_corepos.egg-info/top_level.txt
rattail_corepos/batch/__init__.py
rattail_corepos/batch/coremember.py
rattail_corepos/batch/equityimport.py
rattail_corepos/batch/pos.py
rattail_corepos/batch/vendorcatalog.py
rattail_corepos/corepos/__init__.py
rattail_corepos/corepos/api.py
rattail_corepos/corepos/commands.py
rattail_corepos/corepos/util.py
rattail_corepos/corepos/common/__init__.py
rattail_corepos/corepos/common/importing.py
rattail_corepos/corepos/importing/__init__.py
rattail_corepos/corepos/importing/model.py
rattail_corepos/corepos/importing/rattail.py
rattail_corepos/corepos/importing/db/__init__.py
rattail_corepos/corepos/importing/db/corepos.py
rattail_corepos/corepos/importing/db/csv.py
rattail_corepos/corepos/importing/db/model.py
rattail_corepos/corepos/importing/db/square.py
rattail_corepos/corepos/importing/db/exporters/__init__.py
rattail_corepos/corepos/importing/db/exporters/catapult_inventory.py
rattail_corepos/corepos/importing/db/exporters/catapult_membership.py
rattail_corepos/corepos/importing/db/exporters/csv.py
rattail_corepos/corepos/lane/__init__.py
rattail_corepos/corepos/lane/importing/__init__.py
rattail_corepos/corepos/lane/importing/op/__init__.py
rattail_corepos/corepos/lane/importing/op/model.py
rattail_corepos/corepos/lane/importing/op/office.py
rattail_corepos/corepos/office/__init__.py
rattail_corepos/corepos/office/anonymize.py
rattail_corepos/corepos/office/commands.py
rattail_corepos/corepos/office/patcher.py
rattail_corepos/corepos/office/util.py
rattail_corepos/corepos/office/importing/__init__.py
rattail_corepos/corepos/office/importing/model.py
rattail_corepos/corepos/office/importing/rattail.py
rattail_corepos/corepos/office/importing/db/__init__.py
