Metadata-Version: 2.1
Name: rattail_corepos
Version: 0.2.0
Summary: Rattail Software Interfaces for CORE POS
Home-page: https://rattailproject.org/
Author: Lance Edgar
Author-email: lance@edbob.org
License: GNU GPL v3
Classifier: Development Status :: 3 - Alpha
Classifier: Environment :: Console
Classifier: Environment :: Web Environment
Classifier: Intended Audience :: Developers
Classifier: License :: OSI Approved :: GNU General Public License v3 or later (GPLv3+)
Classifier: Natural Language :: English
Classifier: Operating System :: OS Independent
Classifier: Programming Language :: Python
Classifier: Programming Language :: Python :: 3
Classifier: Programming Language :: Python :: 3.5
Classifier: Topic :: Office/Business
Classifier: Topic :: Software Development :: Libraries :: Python Modules
License-File: COPYING.txt
Requires-Dist: pyCOREPOS
Requires-Dist: rattail
